{
	"entry": [
		{
			"date": "2020-08-17",
			"item": [
				"hrilab.tufts.edu/publications/morovitzetal17vihar.pdf",
				"youtu.be/dnxKo18lETk",
				"dilbert.com"
			]
		},
		{
			"date": "2020-08-16",
			"item": [
				"lo-th.github.io/labs/index.html",
				"dl.acm.org/doi/pdf/10.1145/3371382.3380734",
				"en.wikipedia.org/wiki/Diary_of_Merer"
			]
		},
		{
			"date": "2020-08-15",
			"item": [
				"medium.com/@adityasm20/how-i-built-a-hexapod-robot-b82016d185a5",
				"youtu.be/Dn6b9fCIUpM  Normal Distribution",
				"spellingcity.com/verbs.html",
				"linguasorb.com/english/verbs/most-common-verbs"
			]
		},
		{
			"date": "2020-08-14",
			"item": [
				"robbinmarcus.blogspot.com",
				"metanetsoftware.com/technique/tutorialA.html",
				"dyn4j.org/2010/01/sat",
				"parquet-recordings.com"
			]
		},
		{
			"date": "2020-08-13",
			"item": [
				"professorcook.org/CHAPphysics.pdf",
				"iss-sim.spacex.com",
				"fatsecret.com"
			]
		},
		{
			"date": "2020-08-12",
			"item": [
				"education.github.com/pack",
				"dcode.fr/leet-speak-1337",
				"datatofish.com"
			]
		},
		{
			"date": "2020-08-11",
			"item": [
				"sqlitebrowser.org",
				"thinkingondata.com/5-basic-questions-and-answers-about-high-dimensional-data",
				"infolab.usc.edu/csci599/Fall2007/papers/e-1.pdf"
			]
		},
		{
			"date": "2020-08-10",
			"item": [
				"chrisalbon.com",
				"matplotlib.org/3.1.0/gallery/color/named_colors.html"
			]
		},
		{
			"date": "2020-08-09",
			"item": [
				"reddit.com/r/processing/comments/i6l1fz/coding_from_scratch_procedural_city_builder",
				"city41.github.io/particle.js",
				"mathsisfun.com/data/quartiles.html"
			]
		},
		{
			"date": "2020-08-08",
			"item": [
				"reviseomatic.org/rOmV4",
				"github.com/nbauers/Learn-x86-assembler",
				"reviseomatic.org/help/2-assembler/Assembler%20AQA%20Microcontroller.php"
			]
		},
		{
			"date": "2020-08-07",
			"item": [
				"kubrusly.com/vicente/cores/cores.html",
				"shadertoy.com/view/lscczl",
				"katvlasova.com"
			]
		},
		{
			"date": "2020-08-06",
			"item": [
				"nikonsmallworld.com",
				"blog.bruce-hill.com/6-useful-snippets",
				"github.com/josephg/noisejs"
			]
		},
		{
			"date": "2020-08-05",
			"item": [
				"gist.github.com/xem/7086007",
				"iteral.com/jscrush compress pack",
				"obfuscator.io"
			]
		},
		{
			"date": "2020-08-03",
			"item": [
				"hsluv.org",
				"github.com/hsluv/hsluv/tree/master/javascript",
				"vimeo.com/170519762"
			]
		},
		{
			"date": "2020-08-02",
			"item": [
				"github.com/ysimonson/canvas.js",
				"highlightjs.org/static/demo",
				"stackoverflow.com/questions/2450954/how-to-randomize-shuffle-a-javascript-array"
			]
		},
		{
			"date": "2020-08-01",
			"item": [
				"carbondesignsystem.com",
				"nvie.com/posts/a-successful-git-branching-model",
				"nvie.com/posts/git-power-tools",
				"github.com/nvie/rule-of-law"
			]
		}
	]
}